natlang/__init__.py
natlang/__version__.py
natlang/exporter.py
natlang/fileConverter.py
natlang/fileIO.py
natlang/loader.py
natlang/analysis/__init__.py
natlang/analysis/bash_code_utils.py
natlang/analysis/conllTransformer.py
natlang/analysis/export_bash_seq2seq.py
natlang/analysis/export_conala_to_jsonl.py
natlang/analysis/frameAMR.py
natlang/analysis/merge_bash_data.py
natlang/analysis/pyCodeSyntax.py
natlang/analysis/syntax_checker.py
natlang/analysis/tokenize_bash_intent.py
natlang/format/AMR.py
natlang/format/__init__.py
natlang/format/alignment.py
natlang/format/astTree.py
natlang/format/bashAst.py
natlang/format/bashIntent.py
natlang/format/bashJSON.py
natlang/format/bashTokens.py
natlang/format/conll.py
natlang/format/django.py
natlang/format/intent.py
natlang/format/intentJSON.py
natlang/format/pyCode.py
natlang/format/pyCodeJSON.py
natlang/format/semanticFrame.py
natlang/format/tree.py
natlang/format/txt.py
natlang/format/txtFiles.py
natlang/format/txtOrTree.py
natlang-0.3a29.dist-info/LICENSE
natlang-0.3a29.dist-info/METADATA
natlang-0.3a29.dist-info/WHEEL
natlang-0.3a29.dist-info/top_level.txt
natlang-0.3a29.dist-info/RECORD
