Metadata-Version: 2.1
Name: natlang
Version: 0.3a29
Summary: Natural language data loading tools
Home-page: https://github.com/jeticg/datatool
Author: Jetic Gū, Rory Wang
Author-email: jeticg@sfu.ca
License: UNKNOWN
Platform: UNKNOWN
Classifier: Programming Language :: Python
Classifier: License :: OSI Approved :: MIT License
Classifier: Operating System :: OS Independent
Requires-Dist: jieba
Requires-Dist: progressbar
Requires-Dist: six
Requires-Dist: astor
Requires-Dist: bashlex
